cloud_dataplug-1.0.2.dist-info/licenses/LICENSE
dataplug/__init__.py
dataplug/cloudobject.py
dataplug/entities.py
dataplug/util.py
dataplug/version.py
dataplug/formats/__init__.py
dataplug/formats/astronomics/__init__.py
dataplug/formats/astronomics/ms.py
dataplug/formats/compressed/__init__.py
dataplug/formats/compressed/gzipped.py
dataplug/formats/generic/__init__.py
dataplug/formats/generic/csv.py
dataplug/formats/generic/text.py
dataplug/formats/genomics/__init__.py
dataplug/formats/genomics/fasta.py
dataplug/formats/genomics/fastq.py
dataplug/formats/genomics/vcf.py
dataplug/formats/geospatial/__init__.py
dataplug/formats/geospatial/cog.py
dataplug/formats/geospatial/copc.py
dataplug/formats/geospatial/laspc.py
dataplug/formats/metabolomics/__init__.py
dataplug/formats/metabolomics/imzml.py
dataplug/preprocessing/__init__.py
dataplug/preprocessing/handler.py
dataplug/preprocessing/metadata.py
dataplug/preprocessing/preprocess.py
dataplug/storage/__init__.py
dataplug/storage/filesystem.py
dataplug/storage/picklableS3.py
cloud_dataplug-1.0.2.dist-info/METADATA
cloud_dataplug-1.0.2.dist-info/WHEEL
cloud_dataplug-1.0.2.dist-info/top_level.txt
cloud_dataplug-1.0.2.dist-info/RECORD
