Metadata-Version: 2.4
Name: cloud-dataplug
Version: 1.0.2
Summary: Pluggable data partitioning for cloud-native scientific workloads
Author-email: Aitor Arjona <aitor.a98@gmail.com>
Project-URL: Homepage, https://github.com/CLOUDLAB-URV/dataplug
Classifier: Programming Language :: Python :: 3 :: Only
Classifier: License :: OSI Approved :: Apache Software License
Classifier: Operating System :: OS Independent
Classifier: Development Status :: 2 - Pre-Alpha
Requires-Python: >=3.10
License-File: LICENSE
Requires-Dist: boto3
Requires-Dist: botocore
Requires-Dist: numpy
Requires-Dist: pandas
Requires-Dist: pyarrow
Requires-Dist: smart_open
Requires-Dist: tqdm
Requires-Dist: joblib
Provides-Extra: metabolomics
Requires-Dist: pyimzml; extra == "metabolomics"
Provides-Extra: geospatial
Requires-Dist: laspy; extra == "geospatial"
Requires-Dist: PDAL; extra == "geospatial"
Requires-Dist: rasterio; extra == "geospatial"
Provides-Extra: astronomics
Requires-Dist: casacore; extra == "astronomics"
Dynamic: license-file
